Metadata-Version: 2.1
Name: pyjkernel
Version: 0.1.0
Summary: Python library for Nintendo's JKRArchive/ResourceArchive format
Home-page: https://github.com/SunakazeKun/pyjkernel
Author: Aurum
License: gpl-3.0
Keywords: nintendo,jkernel,rarc,archive,modding
Platform: UNKNOWN
Classifier: Intended Audience :: Developers
Classifier: Topic :: Software Development :: Libraries
Classifier: License :: OSI Approved :: GNU General Public License v3 (GPLv3)
Classifier: Programming Language :: Python :: 3 :: Only
Requires-Python: >=3.6
